sifter/__init__.py
sifter/cli.py
sifter/comparator.py
sifter/parser.py
sifter/py.typed
sifter/utils.py
sifter/commands/__init__.py
sifter/commands/discard.py
sifter/commands/fileinto.py
sifter/commands/if_cmd.py
sifter/commands/imap4flags.py
sifter/commands/keep.py
sifter/commands/notify.py
sifter/commands/redirect.py
sifter/commands/reject.py
sifter/commands/require.py
sifter/commands/stop.py
sifter/commands/variables.py
sifter/comparators/__init__.py
sifter/comparators/ascii_casemap.py
sifter/comparators/octet.py
sifter/extensions/__init__.py
sifter/grammar/__init__.py
sifter/grammar/actions.py
sifter/grammar/command.py
sifter/grammar/command_list.py
sifter/grammar/comparator.py
sifter/grammar/grammar.py
sifter/grammar/lexer.py
sifter/grammar/notificationmethod.py
sifter/grammar/rule.py
sifter/grammar/sieveobject.py
sifter/grammar/state.py
sifter/grammar/string.py
sifter/grammar/tag.py
sifter/grammar/test.py
sifter/grammar/validator.py
sifter/notificationmethods/__init__.py
sifter/notificationmethods/mailto.py
sifter/tests/__init__.py
sifter/tests/address.py
sifter/tests/allof.py
sifter/tests/anyof.py
sifter/tests/body.py
sifter/tests/exists.py
sifter/tests/false.py
sifter/tests/header.py
sifter/tests/ihave.py
sifter/tests/not_test.py
sifter/tests/notify.py
sifter/tests/size.py
sifter/tests/true.py
sifter/validators/__init__.py
sifter/validators/number.py
sifter/validators/stringlist.py
sifter/validators/tag.py
sifter3-0.2.7.dist-info/LICENSE.txt
sifter3-0.2.7.dist-info/METADATA
sifter3-0.2.7.dist-info/WHEEL
sifter3-0.2.7.dist-info/entry_points.txt
sifter3-0.2.7.dist-info/top_level.txt
sifter3-0.2.7.dist-info/RECORD
