Metadata-Version: 2.1
Name: sifter3
Version: 0.2.7
Summary: Parser/evaluator for the Sieve filtering language (RFC 5228) - Python3 version
Home-page: https://sifter3.readthedocs.io/en/latest/
Author: Manfred Kaiser, Gary Peck
Author-email: manfred.kaiser@logfile.at, gary@realify.com
License: BSD
Project-URL: Source, https://github.com/python-sifter/sifter3
Project-URL: Tracker, https://github.com/python-sifter/sifter3/issues
Keywords: sieve email filter parser
Platform: UNKNOWN
Classifier: Programming Language :: Python
Classifier: Programming Language :: Python :: 3
Classifier: Programming Language :: Python :: 3.6
Classifier: Programming Language :: Python :: 3.7
Classifier: Programming Language :: Python :: 3.8
Classifier: License :: OSI Approved :: BSD License
Classifier: Development Status :: 4 - Beta
Classifier: Intended Audience :: Developers
Classifier: Intended Audience :: System Administrators
Classifier: Operating System :: OS Independent
Classifier: Topic :: Communications :: Email :: Filters
Classifier: Topic :: Software Development :: Interpreters
Classifier: Topic :: Software Development :: Libraries :: Python Modules
Requires-Python: >= 3.6
Requires-Dist: ply
